LICENSE
MANIFEST.in
README.md
setup.py
sif/__init__.py
sif/defaults.py
sif/version.py
sif.egg-info/PKG-INFO
sif.egg-info/SOURCES.txt
sif.egg-info/dependency_links.txt
sif.egg-info/entry_points.txt
sif.egg-info/not-zip-safe
sif.egg-info/top_level.txt
sif/client/__init__.py
sif/client/shell.py
sif/header/__init__.py
sif/header/v02/__init__.py
sif/header/v02/descriptors.py
sif/header/v02/globalHeader.py
sif/logger/__init__.py
sif/logger/message.py
sif/logger/namer.py
sif/logger/progress.py
sif/logger/spinner.py
sif/main/__init__.py
sif/main/extra.py
sif/main/header.py
sif/utils/__init__.py
sif/utils/cache.py
sif/utils/fileio.py
sif/utils/names.py
sif/utils/terminal.py